serverless/__init__.py
serverless/serverless_decorator.py
serverless.py-0.0.4.dist-info/METADATA
serverless.py-0.0.4.dist-info/WHEEL
serverless.py-0.0.4.dist-info/top_level.txt
serverless.py-0.0.4.dist-info/RECORD
