Metadata-Version: 2.1
Name: serverless.py
Version: 0.0.4
Summary: A Simple Decorator to create a REST Python API in serverless
Home-page: https://github.com/mtwzim/serverless.py
Author: Matheus Vinícius
Author-email: mtwzim@gmail.com
License: UNKNOWN
Platform: UNKNOWN
Classifier: Programming Language :: Python :: 3.7
Classifier: License :: OSI Approved :: MIT License
Classifier: Operating System :: OS Independent
